{
  "workKey": "blue giant momentum",
  "title": "BLUE GIANT MOMENTUM（1）",
  "author": "石塚 真一/NUMBER8",
  "publisher": "小学館",
  "publishedAt": "2024年02月29日",
  "description": "JAZZの中心地＆最激戦地で頂点目指す！ \n\n 仙台・東京、そしてヨーロッパを経て、アメリカの大地を旅し続けた前作『BLUE GIANT EXPLORER』に続き、ついにマンハッタンに辿りついた大と仲間達がJAZZの頂点を目指す！！ \n\n 【編集担当からのおすすめ情報】 \n 世界のJAZZの中心地にして最激戦区ニューヨークに辿り着いた大たちカルテット。しかしそこではLIVEどころか、日々の生活もままならない厳しい現実が…大たちの新たな挑戦を、同時発売の『BLUE GIANT EXPLORER』9集と併せてお楽しみください！\n『BLUE GIANT MOMENTUM』第1集目次\n\n第1話:NEW YORK,NEW YORK……005\n第2話:COME WHAT MAY……033 \n第3話:WE SEE……057 \n第4話:COMIN' DOWN……081 \n第5話:OVERTURE……105 \n第6話:A NEW JOY……129 \n第7話:HOW WE DO……153 \n第8話:PROCLAMATION……177",
  "image": "https://thumbnail.image.rakuten.co.jp/@0_mall/book/cabinet/7509/9784098627509_1_31.jpg?_ex=200x200",
  "asin": null,
  "amazonUrl": null,
  "tags": {
    "genre": [
      "drama",
      "slice_of_life"
    ],
    "demo": [
      "seinen"
    ],
    "publisher": [
      "p_7c937220"
    ]
  },
  "anilist": {
    "url": "https://anilist.co/manga/164756",
    "genres": [
      "Drama",
      "Music",
      "Slice of Life"
    ],
    "tags": [
      "Seinen",
      "Jazz Music"
    ]
  },
  "vol1": {
    "description": "『BLUE GIANT』（ブルージャイアント）は、石塚真一、NUMBER8による日本の漫画。ジャズを題材とした作品で、『ビッグコミック』（小学館）にて2013年10号から2016年17号まで連載された。第1部の舞台は仙台と東京。同誌2016年18号からはヨーロッパに舞台を移した第2部『BLUE GIANT SUPREME』（ブルージャイアント シュプリーム）が2020年9号まで連載され、同誌2020年11号から2023年10号までアメリカを舞台とした第3部『BLUE GIANT EXPLORER』（ブルージャイアント エクスプローラー）を連載。同誌2023年15号からニューヨーク編である第4部『BLUE GIANT MOMENTUM』（ブルージャイアント モメンタム）が連載されている。\nなお、NUMBER 8はシリーズ連載開始時からの担当編集者であったが、『SUPREME』単行本9巻から正式にstory director（脚本）として参加、のち担当編集を辞め、『MOMENTUM』からはstory（原作・脚本）となる。またアニメ映画の脚本も担当、初の小説となる『ピアノマン「BLUE GIANT」雪祈の物語』（南波永人名義）を執筆している。\nマンガ大賞2016で第3位。2017年、第62回「小学館漫画賞」（一般向け部門）、第20回文化庁メディア芸術祭マンガ部門大賞受賞。2025年10月時点でシリーズ累計部数は1370万部を突破している。2023年2月に劇場アニメ映画版が公開された。\n本作を執筆するにあたり、名門ジャズ・レーベル、ブルーノート・レコードの1950年代から1960年代におけるアルバムジャケットのデザインが大いに参考にされた。\n最初の舞台を仙台にしたのは、石塚の担当編集者（NUMBER 8）が仙台出身であることに加え、ジャズフェスティバルなどを取材し仙台にジャズの土壌があると感じたことも理由としている。"
  }
}