{
  "updatedAt": "2026-02-11T11:31:11.451Z",
  "processedThisRun": 20,
  "items": [
    {
      "seriesKey": "20世紀少年",
      "paapiSearch": {
        "tried": [
          "20世紀少年 (1)",
          "20世紀少年（1）",
          "20世紀少年 1",
          "20世紀少年 1 コミックス",
          "20世紀少年 1 (コミックス)"
        ],
        "results": [
          {
            "query": "20世紀少年 (1)",
            "ok": true,
            "returned": 10,
            "best": {
              "source": "paapi_search",
              "query": "20世紀少年 (1)",
              "title": "20世紀少年: ともだち (1) (ビッグコミックス)",
              "isbn13": "9784091855312",
              "asin": "4091855318",
              "image": "https://m.media-amazon.com/images/I/518o-r7MvpL._SL500_.jpg",
              "score": 650
            }
          },
          {
            "query": "20世紀少年（1）",
            "ok": true,
            "returned": 10,
            "best": {
              "source": "paapi_search",
              "query": "20世紀少年（1）",
              "title": "20世紀少年: ともだち (1) (ビッグコミックス)",
              "isbn13": "9784091855312",
              "asin": "4091855318",
              "image": "https://m.media-amazon.com/images/I/518o-r7MvpL._SL500_.jpg",
              "score": 650
            }
          },
          {
            "query": "20世紀少年 1",
            "ok": true,
            "returned": 10,
            "best": {
              "source": "paapi_search",
              "query": "20世紀少年 1",
              "title": "20世紀少年: ともだち (1) (ビッグコミックス)",
              "isbn13": "9784091855312",
              "asin": "4091855318",
              "image": "https://m.media-amazon.com/images/I/518o-r7MvpL._SL500_.jpg",
              "score": 650
            }
          },
          {
            "query": "20世紀少年 1 コミックス",
            "ok": true,
            "returned": 10,
            "best": {
              "source": "paapi_search",
              "query": "20世紀少年 1 コミックス",
              "title": "20世紀少年: ともだち (1) (ビッグコミックス)",
              "isbn13": "9784091855312",
              "asin": "4091855318",
              "image": "https://m.media-amazon.com/images/I/518o-r7MvpL._SL500_.jpg",
              "score": 650
            }
          },
          {
            "query": "20世紀少年 1 (コミックス)",
            "ok": true,
            "returned": 10,
            "best": {
              "source": "paapi_search",
              "query": "20世紀少年 1 (コミックス)",
              "title": "20世紀少年: ともだち (1) (ビッグコミックス)",
              "isbn13": "9784091855312",
              "asin": "4091855318",
              "image": "https://m.media-amazon.com/images/I/518o-r7MvpL._SL500_.jpg",
              "score": 650
            }
          }
        ],
        "best": {
          "source": "paapi_search",
          "query": "20世紀少年 (1)",
          "title": "20世紀少年: ともだち (1) (ビッグコミックス)",
          "isbn13": "9784091855312",
          "asin": "4091855318",
          "image": "https://m.media-amazon.com/images/I/518o-r7MvpL._SL500_.jpg",
          "score": 650
        }
      },
      "path": "paapi_search_only",
      "confirmed": {
        "seriesKey": "20世紀少年",
        "author": null,
        "vol1": {
          "title": "20世紀少年: ともだち (1) (ビッグコミックス)",
          "isbn13": "9784091855312",
          "asin": "4091855318",
          "image": "https://m.media-amazon.com/images/I/518o-r7MvpL._SL500_.jpg",
          "amazonDp": "https://www.amazon.co.jp/dp/4091855318",
          "source": "paapi_search(mainline_guard)"
        }
      }
    },
    {
      "seriesKey": "ハイキュー！！",
      "paapiSearch": {
        "tried": [
          "ハイキュー！！ (1)",
          "ハイキュー！！（1）",
          "ハイキュー！！ 1",
          "ハイキュー！！ 1 コミックス",
          "ハイキュー！！ 1 (コミックス)"
        ],
        "results": [
          {
            "query": "ハイキュー！！ (1)",
            "ok": true,
            "returned": 10,
            "best": null
          },
          {
            "query": "ハイキュー！！（1）",
            "ok": true,
            "returned": 10,
            "best": null
          },
          {
            "query": "ハイキュー！！ 1",
            "ok": true,
            "returned": 10,
            "best": null
          },
          {
            "query": "ハイキュー！！ 1 コミックス",
            "ok": true,
            "returned": 10,
            "best": null
          },
          {
            "query": "ハイキュー！！ 1 (コミックス)",
            "ok": true,
            "returned": 10,
            "best": null
          }
        ],
        "best": null
      }
    },
    {
      "seriesKey": "東京喰種-トーキョーグール-:re",
      "paapiSearch": {
        "tried": [
          "東京喰種-トーキョーグール-:re (1)",
          "東京喰種-トーキョーグール-:re（1）",
          "東京喰種-トーキョーグール-:re 1",
          "東京喰種-トーキョーグール-:re 1 コミックス",
          "東京喰種-トーキョーグール-:re 1 (コミックス)"
        ],
        "results": [
          {
            "query": "東京喰種-トーキョーグール-:re (1)",
            "ok": true,
            "returned": 10,
            "best": null
          },
          {
            "query": "東京喰種-トーキョーグール-:re（1）",
            "ok": true,
            "returned": 10,
            "best": null
          },
          {
            "query": "東京喰種-トーキョーグール-:re 1",
            "ok": true,
            "returned": 10,
            "best": null
          },
          {
            "query": "東京喰種-トーキョーグール-:re 1 コミックス",
            "ok": true,
            "returned": 10,
            "best": null
          },
          {
            "query": "東京喰種-トーキョーグール-:re 1 (コミックス)",
            "ok": true,
            "returned": 10,
            "best": null
          }
        ],
        "best": null
      }
    },
    {
      "seriesKey": "ジョジョの奇妙な冒険 スティール・ボール・ラン",
      "paapiSearch": {
        "tried": [
          "ジョジョの奇妙な冒険 スティール・ボール・ラン (1)",
          "ジョジョの奇妙な冒険 スティール・ボール・ラン（1）",
          "ジョジョの奇妙な冒険 スティール・ボール・ラン 1",
          "ジョジョの奇妙な冒険 スティール・ボール・ラン 1 コミックス",
          "ジョジョの奇妙な冒険 スティール・ボール・ラン 1 (コミックス)"
        ],
        "results": [
          {
            "query": "ジョジョの奇妙な冒険 スティール・ボール・ラン (1)",
            "ok": true,
            "returned": 10,
            "best": null
          },
          {
            "query": "ジョジョの奇妙な冒険 スティール・ボール・ラン（1）",
            "ok": true,
            "returned": 10,
            "best": null
          },
          {
            "query": "ジョジョの奇妙な冒険 スティール・ボール・ラン 1",
            "ok": true,
            "returned": 10,
            "best": null
          },
          {
            "query": "ジョジョの奇妙な冒険 スティール・ボール・ラン 1 コミックス",
            "ok": true,
            "returned": 10,
            "best": null
          },
          {
            "query": "ジョジョの奇妙な冒険 スティール・ボール・ラン 1 (コミックス)",
            "ok": true,
            "returned": 10,
            "best": null
          }
        ],
        "best": null
      }
    },
    {
      "seriesKey": "ファイアパンチ",
      "paapiSearch": {
        "tried": [
          "ファイアパンチ (1)",
          "ファイアパンチ（1）",
          "ファイアパンチ 1",
          "ファイアパンチ 1 コミックス",
          "ファイアパンチ 1 (コミックス)"
        ],
        "results": [
          {
            "query": "ファイアパンチ (1)",
            "ok": true,
            "returned": 5,
            "best": {
              "source": "paapi_search",
              "query": "ファイアパンチ (1)",
              "title": "ファイアパンチ 1 (ジャンプコミックスDIGITAL)",
              "isbn13": null,
              "asin": "B01G1DV4PY",
              "image": "https://m.media-amazon.com/images/I/51m5nzCQrBL._SL500_.jpg",
              "score": 570
            }
          },
          {
            "query": "ファイアパンチ（1）",
            "ok": true,
            "returned": 5,
            "best": {
              "source": "paapi_search",
              "query": "ファイアパンチ（1）",
              "title": "ファイアパンチ 1 (ジャンプコミックスDIGITAL)",
              "isbn13": null,
              "asin": "B01G1DV4PY",
              "image": "https://m.media-amazon.com/images/I/51m5nzCQrBL._SL500_.jpg",
              "score": 570
            }
          },
          {
            "query": "ファイアパンチ 1",
            "ok": true,
            "returned": 5,
            "best": {
              "source": "paapi_search",
              "query": "ファイアパンチ 1",
              "title": "ファイアパンチ 1 (ジャンプコミックスDIGITAL)",
              "isbn13": null,
              "asin": "B01G1DV4PY",
              "image": "https://m.media-amazon.com/images/I/51m5nzCQrBL._SL500_.jpg",
              "score": 570
            }
          },
          {
            "query": "ファイアパンチ 1 コミックス",
            "ok": true,
            "returned": 5,
            "best": {
              "source": "paapi_search",
              "query": "ファイアパンチ 1 コミックス",
              "title": "ファイアパンチ 1 (ジャンプコミックスDIGITAL)",
              "isbn13": null,
              "asin": "B01G1DV4PY",
              "image": "https://m.media-amazon.com/images/I/51m5nzCQrBL._SL500_.jpg",
              "score": 570
            }
          },
          {
            "query": "ファイアパンチ 1 (コミックス)",
            "ok": true,
            "returned": 5,
            "best": {
              "source": "paapi_search",
              "query": "ファイアパンチ 1 (コミックス)",
              "title": "ファイアパンチ 1 (ジャンプコミックスDIGITAL)",
              "isbn13": null,
              "asin": "B01G1DV4PY",
              "image": "https://m.media-amazon.com/images/I/51m5nzCQrBL._SL500_.jpg",
              "score": 570
            }
          }
        ],
        "best": {
          "source": "paapi_search",
          "query": "ファイアパンチ (1)",
          "title": "ファイアパンチ 1 (ジャンプコミックスDIGITAL)",
          "isbn13": null,
          "asin": "B01G1DV4PY",
          "image": "https://m.media-amazon.com/images/I/51m5nzCQrBL._SL500_.jpg",
          "score": 570
        }
      },
      "paapiGet": {
        "ok": true,
        "json": {
          "ItemsResult": {
            "Items": [
              {
                "ASIN": "B01G1DV4PY",
                "DetailPageURL": "https://www.amazon.co.jp/dp/B01G1DV4PY?tag=book-scout-22&linkCode=ogi&th=1&psc=1",
                "Images": {
                  "Primary": {
                    "Large": {
                      "Height": 500,
                      "URL": "https://m.media-amazon.com/images/I/51m5nzCQrBL._SL500_.jpg",
                      "Width": 368
                    }
                  }
                },
                "ItemInfo": {
                  "ByLineInfo": {
                    "Brand": {
                      "DisplayValue": "集英社",
                      "Label": "Brand",
                      "Locale": "ja_JP"
                    },
                    "Contributors": [
                      {
                        "Locale": "ja_JP",
                        "Name": "藤本タツキ",
                        "Role": "著",
                        "RoleType": "author"
                      }
                    ],
                    "Manufacturer": {
                      "DisplayValue": "集英社",
                      "Label": "Manufacturer",
                      "Locale": "ja_JP"
                    }
                  },
                  "Title": {
                    "DisplayValue": "ファイアパンチ 1 (ジャンプコミックスDIGITAL)",
                    "Label": "Title",
                    "Locale": "ja_JP"
                  }
                }
              }
            ]
          }
        }
      }
    },
    {
      "seriesKey": "NARUTO -ナルト-",
      "paapiSearch": {
        "tried": [
          "NARUTO -ナルト- (1)",
          "NARUTO -ナルト-（1）",
          "NARUTO -ナルト- 1",
          "NARUTO -ナルト- 1 コミックス",
          "NARUTO -ナルト- 1 (コミックス)"
        ],
        "results": [
          {
            "query": "NARUTO -ナルト- (1)",
            "ok": true,
            "returned": 10,
            "best": null
          },
          {
            "query": "NARUTO -ナルト-（1）",
            "ok": true,
            "returned": 10,
            "best": null
          },
          {
            "query": "NARUTO -ナルト- 1",
            "ok": true,
            "returned": 10,
            "best": null
          },
          {
            "query": "NARUTO -ナルト- 1 コミックス",
            "ok": true,
            "returned": 10,
            "best": null
          },
          {
            "query": "NARUTO -ナルト- 1 (コミックス)",
            "ok": true,
            "returned": 10,
            "best": null
          }
        ],
        "best": null
      }
    },
    {
      "seriesKey": "地獄楽",
      "paapiSearch": {
        "tried": [
          "地獄楽 (1)",
          "地獄楽（1）",
          "地獄楽 1",
          "地獄楽 1 コミックス",
          "地獄楽 1 (コミックス)"
        ],
        "results": [
          {
            "query": "地獄楽 (1)",
            "ok": true,
            "returned": 10,
            "best": {
              "source": "paapi_search",
              "query": "地獄楽 (1)",
              "title": "地獄楽 1 (ジャンプコミックスDIGITAL)",
              "isbn13": null,
              "asin": "B079Y75ZF3",
              "image": "https://m.media-amazon.com/images/I/61bLGPnl-4L._SL500_.jpg",
              "score": 570
            }
          },
          {
            "query": "地獄楽（1）",
            "ok": true,
            "returned": 10,
            "best": {
              "source": "paapi_search",
              "query": "地獄楽（1）",
              "title": "地獄楽 1 (ジャンプコミックスDIGITAL)",
              "isbn13": null,
              "asin": "B079Y75ZF3",
              "image": "https://m.media-amazon.com/images/I/61bLGPnl-4L._SL500_.jpg",
              "score": 570
            }
          },
          {
            "query": "地獄楽 1",
            "ok": true,
            "returned": 10,
            "best": {
              "source": "paapi_search",
              "query": "地獄楽 1",
              "title": "地獄楽 1 (ジャンプコミックスDIGITAL)",
              "isbn13": null,
              "asin": "B079Y75ZF3",
              "image": "https://m.media-amazon.com/images/I/61bLGPnl-4L._SL500_.jpg",
              "score": 570
            }
          },
          {
            "query": "地獄楽 1 コミックス",
            "ok": true,
            "returned": 3,
            "best": {
              "source": "paapi_search",
              "query": "地獄楽 1 コミックス",
              "title": "地獄楽 1 (ジャンプコミックスDIGITAL)",
              "isbn13": null,
              "asin": "B079Y75ZF3",
              "image": "https://m.media-amazon.com/images/I/61bLGPnl-4L._SL500_.jpg",
              "score": 570
            }
          },
          {
            "query": "地獄楽 1 (コミックス)",
            "ok": true,
            "returned": 3,
            "best": {
              "source": "paapi_search",
              "query": "地獄楽 1 (コミックス)",
              "title": "地獄楽 1 (ジャンプコミックスDIGITAL)",
              "isbn13": null,
              "asin": "B079Y75ZF3",
              "image": "https://m.media-amazon.com/images/I/61bLGPnl-4L._SL500_.jpg",
              "score": 570
            }
          }
        ],
        "best": {
          "source": "paapi_search",
          "query": "地獄楽 (1)",
          "title": "地獄楽 1 (ジャンプコミックスDIGITAL)",
          "isbn13": null,
          "asin": "B079Y75ZF3",
          "image": "https://m.media-amazon.com/images/I/61bLGPnl-4L._SL500_.jpg",
          "score": 570
        }
      },
      "paapiGet": {
        "ok": true,
        "json": {
          "ItemsResult": {
            "Items": [
              {
                "ASIN": "B079Y75ZF3",
                "DetailPageURL": "https://www.amazon.co.jp/dp/B079Y75ZF3?tag=book-scout-22&linkCode=ogi&th=1&psc=1",
                "Images": {
                  "Primary": {
                    "Large": {
                      "Height": 500,
                      "URL": "https://m.media-amazon.com/images/I/61bLGPnl-4L._SL500_.jpg",
                      "Width": 368
                    }
                  }
                },
                "ItemInfo": {
                  "ByLineInfo": {
                    "Brand": {
                      "DisplayValue": "集英社",
                      "Label": "Brand",
                      "Locale": "ja_JP"
                    },
                    "Contributors": [
                      {
                        "Locale": "ja_JP",
                        "Name": "賀来ゆうじ",
                        "Role": "著",
                        "RoleType": "author"
                      }
                    ],
                    "Manufacturer": {
                      "DisplayValue": "集英社",
                      "Label": "Manufacturer",
                      "Locale": "ja_JP"
                    }
                  },
                  "Title": {
                    "DisplayValue": "地獄楽 1 (ジャンプコミックスDIGITAL)",
                    "Label": "Title",
                    "Locale": "ja_JP"
                  }
                }
              }
            ]
          }
        }
      }
    },
    {
      "seriesKey": "その着せ替え人形は恋をする",
      "paapiSearch": {
        "tried": [
          "その着せ替え人形は恋をする (1)",
          "その着せ替え人形は恋をする（1）",
          "その着せ替え人形は恋をする 1",
          "その着せ替え人形は恋をする 1 コミックス",
          "その着せ替え人形は恋をする 1 (コミックス)"
        ],
        "results": [
          {
            "query": "その着せ替え人形は恋をする (1)",
            "ok": true,
            "returned": 10,
            "best": {
              "source": "paapi_search",
              "query": "その着せ替え人形は恋をする (1)",
              "title": "その着せ替え人形は恋をする(1) (ヤングガンガンコミックス)",
              "isbn13": "9784757559202",
              "asin": "4757559208",
              "image": "https://m.media-amazon.com/images/I/41HRSm+u0DL._SL500_.jpg",
              "score": 650
            }
          },
          {
            "query": "その着せ替え人形は恋をする（1）",
            "ok": true,
            "returned": 10,
            "best": {
              "source": "paapi_search",
              "query": "その着せ替え人形は恋をする（1）",
              "title": "その着せ替え人形は恋をする(1) (ヤングガンガンコミックス)",
              "isbn13": "9784757559202",
              "asin": "4757559208",
              "image": "https://m.media-amazon.com/images/I/41HRSm+u0DL._SL500_.jpg",
              "score": 650
            }
          },
          {
            "query": "その着せ替え人形は恋をする 1",
            "ok": true,
            "returned": 10,
            "best": {
              "source": "paapi_search",
              "query": "その着せ替え人形は恋をする 1",
              "title": "その着せ替え人形は恋をする(1) (ヤングガンガンコミックス)",
              "isbn13": "9784757559202",
              "asin": "4757559208",
              "image": "https://m.media-amazon.com/images/I/41HRSm+u0DL._SL500_.jpg",
              "score": 650
            }
          },
          {
            "query": "その着せ替え人形は恋をする 1 コミックス",
            "ok": true,
            "returned": 10,
            "best": {
              "source": "paapi_search",
              "query": "その着せ替え人形は恋をする 1 コミックス",
              "title": "その着せ替え人形は恋をする(1) (ヤングガンガンコミックス)",
              "isbn13": "9784757559202",
              "asin": "4757559208",
              "image": "https://m.media-amazon.com/images/I/41HRSm+u0DL._SL500_.jpg",
              "score": 650
            }
          },
          {
            "query": "その着せ替え人形は恋をする 1 (コミックス)",
            "ok": true,
            "returned": 10,
            "best": {
              "source": "paapi_search",
              "query": "その着せ替え人形は恋をする 1 (コミックス)",
              "title": "その着せ替え人形は恋をする(1) (ヤングガンガンコミックス)",
              "isbn13": "9784757559202",
              "asin": "4757559208",
              "image": "https://m.media-amazon.com/images/I/41HRSm+u0DL._SL500_.jpg",
              "score": 650
            }
          }
        ],
        "best": {
          "source": "paapi_search",
          "query": "その着せ替え人形は恋をする (1)",
          "title": "その着せ替え人形は恋をする(1) (ヤングガンガンコミックス)",
          "isbn13": "9784757559202",
          "asin": "4757559208",
          "image": "https://m.media-amazon.com/images/I/41HRSm+u0DL._SL500_.jpg",
          "score": 650
        }
      },
      "path": "paapi_search_only",
      "confirmed": {
        "seriesKey": "その着せ替え人形は恋をする",
        "author": null,
        "vol1": {
          "title": "その着せ替え人形は恋をする(1) (ヤングガンガンコミックス)",
          "isbn13": "9784757559202",
          "asin": "4757559208",
          "image": "https://m.media-amazon.com/images/I/41HRSm+u0DL._SL500_.jpg",
          "amazonDp": "https://www.amazon.co.jp/dp/4757559208",
          "source": "paapi_search(mainline_guard)"
        }
      }
    },
    {
      "seriesKey": "聲の形",
      "paapiSearch": {
        "tried": [
          "聲の形 (1)",
          "聲の形（1）",
          "聲の形 1",
          "聲の形 1 コミックス",
          "聲の形 1 (コミックス)"
        ],
        "results": [
          {
            "query": "聲の形 (1)",
            "ok": true,
            "returned": 10,
            "best": {
              "source": "paapi_search",
              "query": "聲の形 (1)",
              "title": "聲の形（１） (週刊少年マガジンコミックス)",
              "isbn13": null,
              "asin": "B00HJYUJ9C",
              "image": "https://m.media-amazon.com/images/I/51VsfzzIY2L._SL500_.jpg",
              "score": 570
            }
          },
          {
            "query": "聲の形（1）",
            "ok": true,
            "returned": 10,
            "best": {
              "source": "paapi_search",
              "query": "聲の形（1）",
              "title": "聲の形（１） (週刊少年マガジンコミックス)",
              "isbn13": null,
              "asin": "B00HJYUJ9C",
              "image": "https://m.media-amazon.com/images/I/51VsfzzIY2L._SL500_.jpg",
              "score": 570
            }
          },
          {
            "query": "聲の形 1",
            "ok": true,
            "returned": 10,
            "best": {
              "source": "paapi_search",
              "query": "聲の形 1",
              "title": "聲の形（１） (週刊少年マガジンコミックス)",
              "isbn13": null,
              "asin": "B00HJYUJ9C",
              "image": "https://m.media-amazon.com/images/I/51VsfzzIY2L._SL500_.jpg",
              "score": 570
            }
          },
          {
            "query": "聲の形 1 コミックス",
            "ok": true,
            "returned": 9,
            "best": {
              "source": "paapi_search",
              "query": "聲の形 1 コミックス",
              "title": "聲の形（１） (週刊少年マガジンコミックス)",
              "isbn13": null,
              "asin": "B00HJYUJ9C",
              "image": "https://m.media-amazon.com/images/I/51VsfzzIY2L._SL500_.jpg",
              "score": 570
            }
          },
          {
            "query": "聲の形 1 (コミックス)",
            "ok": true,
            "returned": 9,
            "best": {
              "source": "paapi_search",
              "query": "聲の形 1 (コミックス)",
              "title": "聲の形（１） (週刊少年マガジンコミックス)",
              "isbn13": null,
              "asin": "B00HJYUJ9C",
              "image": "https://m.media-amazon.com/images/I/51VsfzzIY2L._SL500_.jpg",
              "score": 570
            }
          }
        ],
        "best": {
          "source": "paapi_search",
          "query": "聲の形 (1)",
          "title": "聲の形（１） (週刊少年マガジンコミックス)",
          "isbn13": null,
          "asin": "B00HJYUJ9C",
          "image": "https://m.media-amazon.com/images/I/51VsfzzIY2L._SL500_.jpg",
          "score": 570
        }
      },
      "paapiGet": {
        "ok": true,
        "json": {
          "ItemsResult": {
            "Items": [
              {
                "ASIN": "B00HJYUJ9C",
                "DetailPageURL": "https://www.amazon.co.jp/dp/B00HJYUJ9C?tag=book-scout-22&linkCode=ogi&th=1&psc=1",
                "Images": {
                  "Primary": {
                    "Large": {
                      "Height": 500,
                      "URL": "https://m.media-amazon.com/images/I/51VsfzzIY2L._SL500_.jpg",
                      "Width": 336
                    }
                  }
                },
                "ItemInfo": {
                  "ByLineInfo": {
                    "Contributors": [
                      {
                        "Locale": "ja_JP",
                        "Name": "大今良時",
                        "Role": "著",
                        "RoleType": "author"
                      }
                    ],
                    "Manufacturer": {
                      "DisplayValue": "講談社",
                      "Label": "Manufacturer",
                      "Locale": "ja_JP"
                    }
                  },
                  "Title": {
                    "DisplayValue": "聲の形（１） (週刊少年マガジンコミックス)",
                    "Label": "Title",
                    "Locale": "ja_JP"
                  }
                }
              }
            ]
          }
        }
      }
    },
    {
      "seriesKey": "うずまき",
      "paapiSearch": {
        "tried": [
          "うずまき (1)",
          "うずまき（1）",
          "うずまき 1",
          "うずまき 1 コミックス",
          "うずまき 1 (コミックス)"
        ],
        "results": [
          {
            "query": "うずまき (1)",
            "ok": true,
            "returned": 10,
            "best": {
              "source": "paapi_search",
              "query": "うずまき (1)",
              "title": "きたきた うずまき (0.1.2.えほん)",
              "isbn13": "9784834020953",
              "asin": "4834020959",
              "image": "https://m.media-amazon.com/images/I/51AlcnABk4L._SL500_.jpg",
              "score": 650
            }
          },
          {
            "query": "うずまき（1）",
            "ok": true,
            "returned": 10,
            "best": {
              "source": "paapi_search",
              "query": "うずまき（1）",
              "title": "きたきた うずまき (0.1.2.えほん)",
              "isbn13": "9784834020953",
              "asin": "4834020959",
              "image": "https://m.media-amazon.com/images/I/51AlcnABk4L._SL500_.jpg",
              "score": 650
            }
          },
          {
            "query": "うずまき 1",
            "ok": true,
            "returned": 10,
            "best": {
              "source": "paapi_search",
              "query": "うずまき 1",
              "title": "きたきた うずまき (0.1.2.えほん)",
              "isbn13": "9784834020953",
              "asin": "4834020959",
              "image": "https://m.media-amazon.com/images/I/51AlcnABk4L._SL500_.jpg",
              "score": 650
            }
          },
          {
            "query": "うずまき 1 コミックス",
            "ok": true,
            "returned": 9,
            "best": {
              "source": "paapi_search",
              "query": "うずまき 1 コミックス",
              "title": "うずまき忍術帖 (1) (ダイヤモンドコミックス)",
              "isbn13": "9784790109211",
              "asin": "4790109216",
              "image": "https://m.media-amazon.com/images/I/51wnJXX8TfL._SL500_.jpg",
              "score": 650
            }
          },
          {
            "query": "うずまき 1 (コミックス)",
            "ok": true,
            "returned": 9,
            "best": {
              "source": "paapi_search",
              "query": "うずまき 1 (コミックス)",
              "title": "うずまき忍術帖 (1) (ダイヤモンドコミックス)",
              "isbn13": "9784790109211",
              "asin": "4790109216",
              "image": "https://m.media-amazon.com/images/I/51wnJXX8TfL._SL500_.jpg",
              "score": 650
            }
          }
        ],
        "best": {
          "source": "paapi_search",
          "query": "うずまき (1)",
          "title": "きたきた うずまき (0.1.2.えほん)",
          "isbn13": "9784834020953",
          "asin": "4834020959",
          "image": "https://m.media-amazon.com/images/I/51AlcnABk4L._SL500_.jpg",
          "score": 650
        }
      },
      "path": "paapi_search_only",
      "confirmed": {
        "seriesKey": "うずまき",
        "author": null,
        "vol1": {
          "title": "きたきた うずまき (0.1.2.えほん)",
          "isbn13": "9784834020953",
          "asin": "4834020959",
          "image": "https://m.media-amazon.com/images/I/51AlcnABk4L._SL500_.jpg",
          "amazonDp": "https://www.amazon.co.jp/dp/4834020959",
          "source": "paapi_search(mainline_guard)"
        }
      }
    },
    {
      "seriesKey": "ドロヘドロ",
      "paapiSearch": {
        "tried": [
          "ドロヘドロ (1)",
          "ドロヘドロ（1）",
          "ドロヘドロ 1",
          "ドロヘドロ 1 コミックス",
          "ドロヘドロ 1 (コミックス)"
        ],
        "results": [
          {
            "query": "ドロヘドロ (1)",
            "ok": true,
            "returned": 10,
            "best": {
              "source": "paapi_search",
              "query": "ドロヘドロ (1)",
              "title": "ドロヘドロ（１） (IKKI　COMIX)",
              "isbn13": null,
              "asin": "B07K8QNMMH",
              "image": "https://m.media-amazon.com/images/I/61VI7mFvmKL._SL500_.jpg",
              "score": 570
            }
          },
          {
            "query": "ドロヘドロ（1）",
            "ok": true,
            "returned": 10,
            "best": {
              "source": "paapi_search",
              "query": "ドロヘドロ（1）",
              "title": "ドロヘドロ（１） (IKKI　COMIX)",
              "isbn13": null,
              "asin": "B07K8QNMMH",
              "image": "https://m.media-amazon.com/images/I/61VI7mFvmKL._SL500_.jpg",
              "score": 570
            }
          },
          {
            "query": "ドロヘドロ 1",
            "ok": true,
            "returned": 10,
            "best": {
              "source": "paapi_search",
              "query": "ドロヘドロ 1",
              "title": "ドロヘドロ（１） (IKKI　COMIX)",
              "isbn13": null,
              "asin": "B07K8QNMMH",
              "image": "https://m.media-amazon.com/images/I/61VI7mFvmKL._SL500_.jpg",
              "score": 570
            }
          },
          {
            "query": "ドロヘドロ 1 コミックス",
            "ok": true,
            "returned": 10,
            "best": {
              "source": "paapi_search",
              "query": "ドロヘドロ 1 コミックス",
              "title": "ドロヘドロ（１） (IKKI　COMIX)",
              "isbn13": null,
              "asin": "B07K8QNMMH",
              "image": "https://m.media-amazon.com/images/I/61VI7mFvmKL._SL500_.jpg",
              "score": 570
            }
          },
          {
            "query": "ドロヘドロ 1 (コミックス)",
            "ok": true,
            "returned": 10,
            "best": {
              "source": "paapi_search",
              "query": "ドロヘドロ 1 (コミックス)",
              "title": "ドロヘドロ（１） (IKKI　COMIX)",
              "isbn13": null,
              "asin": "B07K8QNMMH",
              "image": "https://m.media-amazon.com/images/I/61VI7mFvmKL._SL500_.jpg",
              "score": 570
            }
          }
        ],
        "best": {
          "source": "paapi_search",
          "query": "ドロヘドロ (1)",
          "title": "ドロヘドロ（１） (IKKI　COMIX)",
          "isbn13": null,
          "asin": "B07K8QNMMH",
          "image": "https://m.media-amazon.com/images/I/61VI7mFvmKL._SL500_.jpg",
          "score": 570
        }
      },
      "paapiGet": {
        "ok": true,
        "json": {
          "ItemsResult": {
            "Items": [
              {
                "ASIN": "B07K8QNMMH",
                "DetailPageURL": "https://www.amazon.co.jp/dp/B07K8QNMMH?tag=book-scout-22&linkCode=ogi&th=1&psc=1",
                "Images": {
                  "Primary": {
                    "Large": {
                      "Height": 500,
                      "URL": "https://m.media-amazon.com/images/I/61VI7mFvmKL._SL500_.jpg",
                      "Width": 353
                    }
                  }
                },
                "ItemInfo": {
                  "ByLineInfo": {
                    "Brand": {
                      "DisplayValue": "小学館",
                      "Label": "Brand",
                      "Locale": "ja_JP"
                    },
                    "Contributors": [
                      {
                        "Locale": "ja_JP",
                        "Name": "林田球",
                        "Role": "著",
                        "RoleType": "author"
                      }
                    ],
                    "Manufacturer": {
                      "DisplayValue": "小学館",
                      "Label": "Manufacturer",
                      "Locale": "ja_JP"
                    }
                  },
                  "Title": {
                    "DisplayValue": "ドロヘドロ（１） (IKKI　COMIX)",
                    "Label": "Title",
                    "Locale": "ja_JP"
                  }
                }
              }
            ]
          }
        }
      }
    },
    {
      "seriesKey": "寿命を買い取ってもらった。一年につき、一万円で。",
      "paapiSearch": {
        "tried": [
          "寿命を買い取ってもらった。一年につき、一万円で。 (1)",
          "寿命を買い取ってもらった。一年につき、一万円で。（1）",
          "寿命を買い取ってもらった。一年につき、一万円で。 1",
          "寿命を買い取ってもらった。一年につき、一万円で。 1 コミックス",
          "寿命を買い取ってもらった。一年につき、一万円で。 1 (コミックス)"
        ],
        "results": [
          {
            "query": "寿命を買い取ってもらった。一年につき、一万円で。 (1)",
            "ok": true,
            "returned": 5,
            "best": {
              "source": "paapi_search",
              "query": "寿命を買い取ってもらった。一年につき、一万円で。 (1)",
              "title": "寿命を買い取ってもらった。一年につき、一万円で。 1 (ジャンプコミックスDIGITAL)",
              "isbn13": null,
              "asin": "B072J3Z7YP",
              "image": "https://m.media-amazon.com/images/I/51lNgVTyXCL._SL500_.jpg",
              "score": 570
            }
          },
          {
            "query": "寿命を買い取ってもらった。一年につき、一万円で。（1）",
            "ok": true,
            "returned": 5,
            "best": {
              "source": "paapi_search",
              "query": "寿命を買い取ってもらった。一年につき、一万円で。（1）",
              "title": "寿命を買い取ってもらった。一年につき、一万円で。 1 (ジャンプコミックスDIGITAL)",
              "isbn13": null,
              "asin": "B072J3Z7YP",
              "image": "https://m.media-amazon.com/images/I/51lNgVTyXCL._SL500_.jpg",
              "score": 570
            }
          },
          {
            "query": "寿命を買い取ってもらった。一年につき、一万円で。 1",
            "ok": true,
            "returned": 5,
            "best": {
              "source": "paapi_search",
              "query": "寿命を買い取ってもらった。一年につき、一万円で。 1",
              "title": "寿命を買い取ってもらった。一年につき、一万円で。 1 (ジャンプコミックスDIGITAL)",
              "isbn13": null,
              "asin": "B072J3Z7YP",
              "image": "https://m.media-amazon.com/images/I/51lNgVTyXCL._SL500_.jpg",
              "score": 570
            }
          },
          {
            "query": "寿命を買い取ってもらった。一年につき、一万円で。 1 コミックス",
            "ok": true,
            "returned": 3,
            "best": {
              "source": "paapi_search",
              "query": "寿命を買い取ってもらった。一年につき、一万円で。 1 コミックス",
              "title": "寿命を買い取ってもらった。一年につき、一万円で。 1 (ジャンプコミックスDIGITAL)",
              "isbn13": null,
              "asin": "B072J3Z7YP",
              "image": "https://m.media-amazon.com/images/I/51lNgVTyXCL._SL500_.jpg",
              "score": 570
            }
          },
          {
            "query": "寿命を買い取ってもらった。一年につき、一万円で。 1 (コミックス)",
            "ok": true,
            "returned": 3,
            "best": {
              "source": "paapi_search",
              "query": "寿命を買い取ってもらった。一年につき、一万円で。 1 (コミックス)",
              "title": "寿命を買い取ってもらった。一年につき、一万円で。 1 (ジャンプコミックスDIGITAL)",
              "isbn13": null,
              "asin": "B072J3Z7YP",
              "image": "https://m.media-amazon.com/images/I/51lNgVTyXCL._SL500_.jpg",
              "score": 570
            }
          }
        ],
        "best": {
          "source": "paapi_search",
          "query": "寿命を買い取ってもらった。一年につき、一万円で。 (1)",
          "title": "寿命を買い取ってもらった。一年につき、一万円で。 1 (ジャンプコミックスDIGITAL)",
          "isbn13": null,
          "asin": "B072J3Z7YP",
          "image": "https://m.media-amazon.com/images/I/51lNgVTyXCL._SL500_.jpg",
          "score": 570
        }
      },
      "paapiGet": {
        "ok": true,
        "json": {
          "ItemsResult": {
            "Items": [
              {
                "ASIN": "B072J3Z7YP",
                "DetailPageURL": "https://www.amazon.co.jp/dp/B072J3Z7YP?tag=book-scout-22&linkCode=ogi&th=1&psc=1",
                "Images": {
                  "Primary": {
                    "Large": {
                      "Height": 500,
                      "URL": "https://m.media-amazon.com/images/I/51lNgVTyXCL._SL500_.jpg",
                      "Width": 368
                    }
                  }
                },
                "ItemInfo": {
                  "ByLineInfo": {
                    "Brand": {
                      "DisplayValue": "集英社",
                      "Label": "Brand",
                      "Locale": "ja_JP"
                    },
                    "Contributors": [
                      {
                        "Locale": "ja_JP",
                        "Name": "三秋縋（メディアワークス文庫「三日間の幸福」）",
                        "Role": "著",
                        "RoleType": "author"
                      },
                      {
                        "Locale": "ja_JP",
                        "Name": "田口囁一",
                        "Role": "著",
                        "RoleType": "author"
                      },
                      {
                        "Locale": "ja_JP",
                        "Name": "E9L・田口囁一",
                        "Role": "著",
                        "RoleType": "author"
                      }
                    ],
                    "Manufacturer": {
                      "DisplayValue": "集英社",
                      "Label": "Manufacturer",
                      "Locale": "ja_JP"
                    }
                  },
                  "Title": {
                    "DisplayValue": "寿命を買い取ってもらった。一年につき、一万円で。 1 (ジャンプコミックスDIGITAL)",
                    "Label": "Title",
                    "Locale": "ja_JP"
                  }
                }
              }
            ]
          }
        }
      }
    },
    {
      "seriesKey": "宝石の国",
      "paapiSearch": {
        "tried": [
          "宝石の国 (1)",
          "宝石の国（1）",
          "宝石の国 1",
          "宝石の国 1 コミックス",
          "宝石の国 1 (コミックス)"
        ],
        "results": [
          {
            "query": "宝石の国 (1)",
            "ok": true,
            "returned": 10,
            "best": {
              "source": "paapi_search",
              "query": "宝石の国 (1)",
              "title": "宝石の国（１） (アフタヌーンコミックス)",
              "isbn13": null,
              "asin": "B00DW4ZYBG",
              "image": "https://m.media-amazon.com/images/I/61FXZ-+RZLL._SL500_.jpg",
              "score": 570
            }
          },
          {
            "query": "宝石の国（1）",
            "ok": true,
            "returned": 10,
            "best": {
              "source": "paapi_search",
              "query": "宝石の国（1）",
              "title": "宝石の国（１） (アフタヌーンコミックス)",
              "isbn13": null,
              "asin": "B00DW4ZYBG",
              "image": "https://m.media-amazon.com/images/I/61FXZ-+RZLL._SL500_.jpg",
              "score": 570
            }
          },
          {
            "query": "宝石の国 1",
            "ok": true,
            "returned": 10,
            "best": {
              "source": "paapi_search",
              "query": "宝石の国 1",
              "title": "宝石の国（１） (アフタヌーンコミックス)",
              "isbn13": null,
              "asin": "B00DW4ZYBG",
              "image": "https://m.media-amazon.com/images/I/61FXZ-+RZLL._SL500_.jpg",
              "score": 570
            }
          },
          {
            "query": "宝石の国 1 コミックス",
            "ok": true,
            "returned": 5,
            "best": {
              "source": "paapi_search",
              "query": "宝石の国 1 コミックス",
              "title": "宝石の国（１） (アフタヌーンコミックス)",
              "isbn13": null,
              "asin": "B00DW4ZYBG",
              "image": "https://m.media-amazon.com/images/I/61FXZ-+RZLL._SL500_.jpg",
              "score": 570
            }
          },
          {
            "query": "宝石の国 1 (コミックス)",
            "ok": true,
            "returned": 5,
            "best": {
              "source": "paapi_search",
              "query": "宝石の国 1 (コミックス)",
              "title": "宝石の国（１） (アフタヌーンコミックス)",
              "isbn13": null,
              "asin": "B00DW4ZYBG",
              "image": "https://m.media-amazon.com/images/I/61FXZ-+RZLL._SL500_.jpg",
              "score": 570
            }
          }
        ],
        "best": {
          "source": "paapi_search",
          "query": "宝石の国 (1)",
          "title": "宝石の国（１） (アフタヌーンコミックス)",
          "isbn13": null,
          "asin": "B00DW4ZYBG",
          "image": "https://m.media-amazon.com/images/I/61FXZ-+RZLL._SL500_.jpg",
          "score": 570
        }
      },
      "paapiGet": {
        "ok": true,
        "json": {
          "ItemsResult": {
            "Items": [
              {
                "ASIN": "B00DW4ZYBG",
                "DetailPageURL": "https://www.amazon.co.jp/dp/B00DW4ZYBG?tag=book-scout-22&linkCode=ogi&th=1&psc=1",
                "Images": {
                  "Primary": {
                    "Large": {
                      "Height": 500,
                      "URL": "https://m.media-amazon.com/images/I/61FXZ-+RZLL._SL500_.jpg",
                      "Width": 352
                    }
                  }
                },
                "ItemInfo": {
                  "ByLineInfo": {
                    "Brand": {
                      "DisplayValue": "講談社",
                      "Label": "Brand",
                      "Locale": "ja_JP"
                    },
                    "Contributors": [
                      {
                        "Locale": "ja_JP",
                        "Name": "市川春子",
                        "Role": "著",
                        "RoleType": "author"
                      }
                    ],
                    "Manufacturer": {
                      "DisplayValue": "講談社",
                      "Label": "Manufacturer",
                      "Locale": "ja_JP"
                    }
                  },
                  "Title": {
                    "DisplayValue": "宝石の国（１） (アフタヌーンコミックス)",
                    "Label": "Title",
                    "Locale": "ja_JP"
                  }
                }
              }
            ]
          }
        }
      }
    },
    {
      "seriesKey": "鋼の錬金術師",
      "paapiSearch": {
        "tried": [
          "鋼の錬金術師 (1)",
          "鋼の錬金術師（1）",
          "鋼の錬金術師 1",
          "鋼の錬金術師 1 コミックス",
          "鋼の錬金術師 1 (コミックス)"
        ],
        "results": [
          {
            "query": "鋼の錬金術師 (1)",
            "ok": true,
            "returned": 10,
            "best": {
              "source": "paapi_search",
              "query": "鋼の錬金術師 (1)",
              "title": "TVアニメ 鋼の錬金術師シナリオブック (1)",
              "isbn13": "9784757512689",
              "asin": "4757512686",
              "image": "https://m.media-amazon.com/images/I/510X5Gi6kyL._SL500_.jpg",
              "score": 650
            }
          },
          {
            "query": "鋼の錬金術師（1）",
            "ok": true,
            "returned": 10,
            "best": {
              "source": "paapi_search",
              "query": "鋼の錬金術師（1）",
              "title": "TVアニメ 鋼の錬金術師シナリオブック (1)",
              "isbn13": "9784757512689",
              "asin": "4757512686",
              "image": "https://m.media-amazon.com/images/I/510X5Gi6kyL._SL500_.jpg",
              "score": 650
            }
          },
          {
            "query": "鋼の錬金術師 1",
            "ok": true,
            "returned": 10,
            "best": {
              "source": "paapi_search",
              "query": "鋼の錬金術師 1",
              "title": "鋼の錬金術師1巻~4巻 バリューパック (ガンガンコミックス)",
              "isbn13": "9784757578777",
              "asin": "4757578776",
              "image": "https://m.media-amazon.com/images/I/61OsSH0ckRL._SL500_.jpg",
              "score": 650
            }
          },
          {
            "query": "鋼の錬金術師 1 コミックス",
            "ok": true,
            "returned": 10,
            "best": {
              "source": "paapi_search",
              "query": "鋼の錬金術師 1 コミックス",
              "title": "鋼の錬金術師 Vol.1 二人の錬金術師 (ガンガンコミックスリミックス)",
              "isbn13": "9784757525559",
              "asin": "4757525559",
              "image": "https://m.media-amazon.com/images/I/61mDWueg+RL._SL500_.jpg",
              "score": 650
            }
          },
          {
            "query": "鋼の錬金術師 1 (コミックス)",
            "ok": true,
            "returned": 10,
            "best": {
              "source": "paapi_search",
              "query": "鋼の錬金術師 1 (コミックス)",
              "title": "鋼の錬金術師 Vol.1 二人の錬金術師 (ガンガンコミックスリミックス)",
              "isbn13": "9784757525559",
              "asin": "4757525559",
              "image": "https://m.media-amazon.com/images/I/61mDWueg+RL._SL500_.jpg",
              "score": 650
            }
          }
        ],
        "best": {
          "source": "paapi_search",
          "query": "鋼の錬金術師 (1)",
          "title": "TVアニメ 鋼の錬金術師シナリオブック (1)",
          "isbn13": "9784757512689",
          "asin": "4757512686",
          "image": "https://m.media-amazon.com/images/I/510X5Gi6kyL._SL500_.jpg",
          "score": 650
        }
      },
      "path": "paapi_search_only",
      "confirmed": {
        "seriesKey": "鋼の錬金術師",
        "author": null,
        "vol1": {
          "title": "TVアニメ 鋼の錬金術師シナリオブック (1)",
          "isbn13": "9784757512689",
          "asin": "4757512686",
          "image": "https://m.media-amazon.com/images/I/510X5Gi6kyL._SL500_.jpg",
          "amazonDp": "https://www.amazon.co.jp/dp/4757512686",
          "source": "paapi_search(mainline_guard)"
        }
      }
    },
    {
      "seriesKey": "ブルーピリオド",
      "paapiSearch": {
        "tried": [
          "ブルーピリオド (1)",
          "ブルーピリオド（1）",
          "ブルーピリオド 1",
          "ブルーピリオド 1 コミックス",
          "ブルーピリオド 1 (コミックス)"
        ],
        "results": [
          {
            "query": "ブルーピリオド (1)",
            "ok": true,
            "returned": 10,
            "best": {
              "source": "paapi_search",
              "query": "ブルーピリオド (1)",
              "title": "ブルーピリオド(1)実写映画化記念特装版 (プレミアムKC)",
              "isbn13": "9784065368381",
              "asin": "4065368383",
              "image": "https://m.media-amazon.com/images/I/51a+bIUSRCL._SL500_.jpg",
              "score": 650
            }
          },
          {
            "query": "ブルーピリオド（1）",
            "ok": true,
            "returned": 10,
            "best": {
              "source": "paapi_search",
              "query": "ブルーピリオド（1）",
              "title": "ブルーピリオド(1)実写映画化記念特装版 (プレミアムKC)",
              "isbn13": "9784065368381",
              "asin": "4065368383",
              "image": "https://m.media-amazon.com/images/I/51a+bIUSRCL._SL500_.jpg",
              "score": 650
            }
          },
          {
            "query": "ブルーピリオド 1",
            "ok": true,
            "returned": 10,
            "best": {
              "source": "paapi_search",
              "query": "ブルーピリオド 1",
              "title": "ブルーピリオド(1)実写映画化記念特装版 (プレミアムKC)",
              "isbn13": "9784065368381",
              "asin": "4065368383",
              "image": "https://m.media-amazon.com/images/I/51a+bIUSRCL._SL500_.jpg",
              "score": 650
            }
          },
          {
            "query": "ブルーピリオド 1 コミックス",
            "ok": true,
            "returned": 10,
            "best": {
              "source": "paapi_search",
              "query": "ブルーピリオド 1 コミックス",
              "title": "ブルーピリオド（１） (アフタヌーンコミックス)",
              "isbn13": null,
              "asin": "B07873642C",
              "image": "https://m.media-amazon.com/images/I/51DyNWXnnuL._SL500_.jpg",
              "score": 570
            }
          },
          {
            "query": "ブルーピリオド 1 (コミックス)",
            "ok": true,
            "returned": 10,
            "best": {
              "source": "paapi_search",
              "query": "ブルーピリオド 1 (コミックス)",
              "title": "ブルーピリオド（１） (アフタヌーンコミックス)",
              "isbn13": null,
              "asin": "B07873642C",
              "image": "https://m.media-amazon.com/images/I/51DyNWXnnuL._SL500_.jpg",
              "score": 570
            }
          }
        ],
        "best": {
          "source": "paapi_search",
          "query": "ブルーピリオド (1)",
          "title": "ブルーピリオド(1)実写映画化記念特装版 (プレミアムKC)",
          "isbn13": "9784065368381",
          "asin": "4065368383",
          "image": "https://m.media-amazon.com/images/I/51a+bIUSRCL._SL500_.jpg",
          "score": 650
        }
      },
      "path": "paapi_search_only",
      "confirmed": {
        "seriesKey": "ブルーピリオド",
        "author": null,
        "vol1": {
          "title": "ブルーピリオド(1)実写映画化記念特装版 (プレミアムKC)",
          "isbn13": "9784065368381",
          "asin": "4065368383",
          "image": "https://m.media-amazon.com/images/I/51a+bIUSRCL._SL500_.jpg",
          "amazonDp": "https://www.amazon.co.jp/dp/4065368383",
          "source": "paapi_search(mainline_guard)"
        }
      }
    },
    {
      "seriesKey": "イジらないで、長瀞さん",
      "paapiSearch": {
        "tried": [
          "イジらないで、長瀞さん (1)",
          "イジらないで、長瀞さん（1）",
          "イジらないで、長瀞さん 1",
          "イジらないで、長瀞さん 1 コミックス",
          "イジらないで、長瀞さん 1 (コミックス)"
        ],
        "results": [
          {
            "query": "イジらないで、長瀞さん (1)",
            "ok": true,
            "returned": 10,
            "best": {
              "source": "paapi_search",
              "query": "イジらないで、長瀞さん (1)",
              "title": "イジらないで、長瀞さん（１） (マガジンポケットコミックス)",
              "isbn13": null,
              "asin": "B07B3VQQFJ",
              "image": "https://m.media-amazon.com/images/I/51zny95UtDL._SL500_.jpg",
              "score": 570
            }
          },
          {
            "query": "イジらないで、長瀞さん（1）",
            "ok": true,
            "returned": 10,
            "best": {
              "source": "paapi_search",
              "query": "イジらないで、長瀞さん（1）",
              "title": "イジらないで、長瀞さん（１） (マガジンポケットコミックス)",
              "isbn13": null,
              "asin": "B07B3VQQFJ",
              "image": "https://m.media-amazon.com/images/I/51zny95UtDL._SL500_.jpg",
              "score": 570
            }
          },
          {
            "query": "イジらないで、長瀞さん 1",
            "ok": true,
            "returned": 10,
            "best": {
              "source": "paapi_search",
              "query": "イジらないで、長瀞さん 1",
              "title": "イジらないで、長瀞さん（１） (マガジンポケットコミックス)",
              "isbn13": null,
              "asin": "B07B3VQQFJ",
              "image": "https://m.media-amazon.com/images/I/51zny95UtDL._SL500_.jpg",
              "score": 570
            }
          },
          {
            "query": "イジらないで、長瀞さん 1 コミックス",
            "ok": true,
            "returned": 7,
            "best": {
              "source": "paapi_search",
              "query": "イジらないで、長瀞さん 1 コミックス",
              "title": "イジらないで、長瀞さん（１） (マガジンポケットコミックス)",
              "isbn13": null,
              "asin": "B07B3VQQFJ",
              "image": "https://m.media-amazon.com/images/I/51zny95UtDL._SL500_.jpg",
              "score": 570
            }
          },
          {
            "query": "イジらないで、長瀞さん 1 (コミックス)",
            "ok": true,
            "returned": 7,
            "best": {
              "source": "paapi_search",
              "query": "イジらないで、長瀞さん 1 (コミックス)",
              "title": "イジらないで、長瀞さん（１） (マガジンポケットコミックス)",
              "isbn13": null,
              "asin": "B07B3VQQFJ",
              "image": "https://m.media-amazon.com/images/I/51zny95UtDL._SL500_.jpg",
              "score": 570
            }
          }
        ],
        "best": {
          "source": "paapi_search",
          "query": "イジらないで、長瀞さん (1)",
          "title": "イジらないで、長瀞さん（１） (マガジンポケットコミックス)",
          "isbn13": null,
          "asin": "B07B3VQQFJ",
          "image": "https://m.media-amazon.com/images/I/51zny95UtDL._SL500_.jpg",
          "score": 570
        }
      },
      "paapiGet": {
        "ok": true,
        "json": {
          "ItemsResult": {
            "Items": [
              {
                "ASIN": "B07B3VQQFJ",
                "DetailPageURL": "https://www.amazon.co.jp/dp/B07B3VQQFJ?tag=book-scout-22&linkCode=ogi&th=1&psc=1",
                "Images": {
                  "Primary": {
                    "Large": {
                      "Height": 500,
                      "URL": "https://m.media-amazon.com/images/I/51zny95UtDL._SL500_.jpg",
                      "Width": 378
                    }
                  }
                },
                "ItemInfo": {
                  "ByLineInfo": {
                    "Brand": {
                      "DisplayValue": "講談社",
                      "Label": "Brand",
                      "Locale": "ja_JP"
                    },
                    "Contributors": [
                      {
                        "Locale": "ja_JP",
                        "Name": "ナナシ",
                        "Role": "著",
                        "RoleType": "author"
                      }
                    ],
                    "Manufacturer": {
                      "DisplayValue": "講談社",
                      "Label": "Manufacturer",
                      "Locale": "ja_JP"
                    }
                  },
                  "Title": {
                    "DisplayValue": "イジらないで、長瀞さん（１） (マガジンポケットコミックス)",
                    "Label": "Title",
                    "Locale": "ja_JP"
                  }
                }
              }
            ]
          }
        }
      }
    },
    {
      "seriesKey": "キングダム",
      "paapiSearch": {
        "tried": [
          "キングダム (1)",
          "キングダム（1）",
          "キングダム 1",
          "キングダム 1 コミックス",
          "キングダム 1 (コミックス)"
        ],
        "results": [
          {
            "query": "キングダム (1)",
            "ok": true,
            "returned": 10,
            "best": {
              "source": "paapi_search",
              "query": "キングダム (1)",
              "title": "キングダム 完全版 1 (愛蔵版コミックス)",
              "isbn13": "9784087927863",
              "asin": "4087927865",
              "image": "https://m.media-amazon.com/images/I/51qP1djrNhL._SL500_.jpg",
              "score": 650
            }
          },
          {
            "query": "キングダム（1）",
            "ok": true,
            "returned": 10,
            "best": {
              "source": "paapi_search",
              "query": "キングダム（1）",
              "title": "キングダム 完全版 1 (愛蔵版コミックス)",
              "isbn13": "9784087927863",
              "asin": "4087927865",
              "image": "https://m.media-amazon.com/images/I/51qP1djrNhL._SL500_.jpg",
              "score": 650
            }
          },
          {
            "query": "キングダム 1",
            "ok": true,
            "returned": 10,
            "best": {
              "source": "paapi_search",
              "query": "キングダム 1",
              "title": "キングダム 完全版 1 (愛蔵版コミックス)",
              "isbn13": "9784087927863",
              "asin": "4087927865",
              "image": "https://m.media-amazon.com/images/I/51qP1djrNhL._SL500_.jpg",
              "score": 650
            }
          },
          {
            "query": "キングダム 1 コミックス",
            "ok": true,
            "returned": 10,
            "best": {
              "source": "paapi_search",
              "query": "キングダム 1 コミックス",
              "title": "キングダム 完全版 1 (愛蔵版コミックス)",
              "isbn13": "9784087927863",
              "asin": "4087927865",
              "image": "https://m.media-amazon.com/images/I/51qP1djrNhL._SL500_.jpg",
              "score": 650
            }
          },
          {
            "query": "キングダム 1 (コミックス)",
            "ok": true,
            "returned": 10,
            "best": {
              "source": "paapi_search",
              "query": "キングダム 1 (コミックス)",
              "title": "キングダム 完全版 1 (愛蔵版コミックス)",
              "isbn13": "9784087927863",
              "asin": "4087927865",
              "image": "https://m.media-amazon.com/images/I/51qP1djrNhL._SL500_.jpg",
              "score": 650
            }
          }
        ],
        "best": {
          "source": "paapi_search",
          "query": "キングダム (1)",
          "title": "キングダム 完全版 1 (愛蔵版コミックス)",
          "isbn13": "9784087927863",
          "asin": "4087927865",
          "image": "https://m.media-amazon.com/images/I/51qP1djrNhL._SL500_.jpg",
          "score": 650
        }
      },
      "path": "paapi_search_only",
      "confirmed": {
        "seriesKey": "キングダム",
        "author": null,
        "vol1": {
          "title": "キングダム 完全版 1 (愛蔵版コミックス)",
          "isbn13": "9784087927863",
          "asin": "4087927865",
          "image": "https://m.media-amazon.com/images/I/51qP1djrNhL._SL500_.jpg",
          "amazonDp": "https://www.amazon.co.jp/dp/4087927865",
          "source": "paapi_search(mainline_guard)"
        }
      }
    },
    {
      "seriesKey": "ジョジョの奇妙な冒険 ストーンオーシャン",
      "paapiSearch": {
        "tried": [
          "ジョジョの奇妙な冒険 ストーンオーシャン (1)",
          "ジョジョの奇妙な冒険 ストーンオーシャン（1）",
          "ジョジョの奇妙な冒険 ストーンオーシャン 1",
          "ジョジョの奇妙な冒険 ストーンオーシャン 1 コミックス",
          "ジョジョの奇妙な冒険 ストーンオーシャン 1 (コミックス)"
        ],
        "results": [
          {
            "query": "ジョジョの奇妙な冒険 ストーンオーシャン (1)",
            "ok": true,
            "returned": 10,
            "best": null
          },
          {
            "query": "ジョジョの奇妙な冒険 ストーンオーシャン（1）",
            "ok": true,
            "returned": 10,
            "best": null
          },
          {
            "query": "ジョジョの奇妙な冒険 ストーンオーシャン 1",
            "ok": true,
            "returned": 10,
            "best": null
          },
          {
            "query": "ジョジョの奇妙な冒険 ストーンオーシャン 1 コミックス",
            "ok": true,
            "returned": 5,
            "best": null
          },
          {
            "query": "ジョジョの奇妙な冒険 ストーンオーシャン 1 (コミックス)",
            "ok": true,
            "returned": 5,
            "best": null
          }
        ],
        "best": null
      }
    },
    {
      "seriesKey": "地縛少年 花子くん",
      "paapiSearch": {
        "tried": [
          "地縛少年 花子くん (1)",
          "地縛少年 花子くん（1）",
          "地縛少年 花子くん 1",
          "地縛少年 花子くん 1 コミックス",
          "地縛少年 花子くん 1 (コミックス)"
        ],
        "results": [
          {
            "query": "地縛少年 花子くん (1)",
            "ok": true,
            "returned": 10,
            "best": {
              "source": "paapi_search",
              "query": "地縛少年 花子くん (1)",
              "title": "地縛少年 花子くん 1巻 (デジタル版Gファンタジーコミックス)",
              "isbn13": null,
              "asin": "B00WVRC6JI",
              "image": "https://m.media-amazon.com/images/I/51PwNVwbmCL._SL500_.jpg",
              "score": 570
            }
          },
          {
            "query": "地縛少年 花子くん（1）",
            "ok": true,
            "returned": 10,
            "best": {
              "source": "paapi_search",
              "query": "地縛少年 花子くん（1）",
              "title": "地縛少年 花子くん 1巻 (デジタル版Gファンタジーコミックス)",
              "isbn13": null,
              "asin": "B00WVRC6JI",
              "image": "https://m.media-amazon.com/images/I/51PwNVwbmCL._SL500_.jpg",
              "score": 570
            }
          },
          {
            "query": "地縛少年 花子くん 1",
            "ok": true,
            "returned": 10,
            "best": {
              "source": "paapi_search",
              "query": "地縛少年 花子くん 1",
              "title": "地縛少年 花子くん 1巻 (デジタル版Gファンタジーコミックス)",
              "isbn13": null,
              "asin": "B00WVRC6JI",
              "image": "https://m.media-amazon.com/images/I/51PwNVwbmCL._SL500_.jpg",
              "score": 570
            }
          },
          {
            "query": "地縛少年 花子くん 1 コミックス",
            "ok": true,
            "returned": 10,
            "best": {
              "source": "paapi_search",
              "query": "地縛少年 花子くん 1 コミックス",
              "title": "地縛少年 花子くん 1巻~3巻バリューパック (Gファンタジーコミックス)",
              "isbn13": "9784757595781",
              "asin": "4757595786",
              "image": "https://m.media-amazon.com/images/I/51MGfohEgIL._SL500_.jpg",
              "score": 650
            }
          },
          {
            "query": "地縛少年 花子くん 1 (コミックス)",
            "ok": true,
            "returned": 10,
            "best": {
              "source": "paapi_search",
              "query": "地縛少年 花子くん 1 (コミックス)",
              "title": "地縛少年 花子くん 1巻~3巻バリューパック (Gファンタジーコミックス)",
              "isbn13": "9784757595781",
              "asin": "4757595786",
              "image": "https://m.media-amazon.com/images/I/51MGfohEgIL._SL500_.jpg",
              "score": 650
            }
          }
        ],
        "best": {
          "source": "paapi_search",
          "query": "地縛少年 花子くん 1 コミックス",
          "title": "地縛少年 花子くん 1巻~3巻バリューパック (Gファンタジーコミックス)",
          "isbn13": "9784757595781",
          "asin": "4757595786",
          "image": "https://m.media-amazon.com/images/I/51MGfohEgIL._SL500_.jpg",
          "score": 650
        }
      },
      "path": "paapi_search_only",
      "confirmed": {
        "seriesKey": "地縛少年 花子くん",
        "author": null,
        "vol1": {
          "title": "地縛少年 花子くん 1巻~3巻バリューパック (Gファンタジーコミックス)",
          "isbn13": "9784757595781",
          "asin": "4757595786",
          "image": "https://m.media-amazon.com/images/I/51MGfohEgIL._SL500_.jpg",
          "amazonDp": "https://www.amazon.co.jp/dp/4757595786",
          "source": "paapi_search(mainline_guard)"
        }
      }
    },
    {
      "seriesKey": "薫る花は凛と咲く",
      "paapiSearch": {
        "tried": [
          "薫る花は凛と咲く (1)",
          "薫る花は凛と咲く（1）",
          "薫る花は凛と咲く 1",
          "薫る花は凛と咲く 1 コミックス",
          "薫る花は凛と咲く 1 (コミックス)"
        ],
        "results": [
          {
            "query": "薫る花は凛と咲く (1)",
            "ok": true,
            "returned": 10,
            "best": {
              "source": "paapi_search",
              "query": "薫る花は凛と咲く (1)",
              "title": "薫る花は凛と咲く（１） (マガジンポケットコミックス)",
              "isbn13": null,
              "asin": "B09TF1DNJZ",
              "image": "https://m.media-amazon.com/images/I/51ZHjkFQUSL._SL500_.jpg",
              "score": 570
            }
          },
          {
            "query": "薫る花は凛と咲く（1）",
            "ok": true,
            "returned": 10,
            "best": {
              "source": "paapi_search",
              "query": "薫る花は凛と咲く（1）",
              "title": "薫る花は凛と咲く（１） (マガジンポケットコミックス)",
              "isbn13": null,
              "asin": "B09TF1DNJZ",
              "image": "https://m.media-amazon.com/images/I/51ZHjkFQUSL._SL500_.jpg",
              "score": 570
            }
          },
          {
            "query": "薫る花は凛と咲く 1",
            "ok": true,
            "returned": 10,
            "best": {
              "source": "paapi_search",
              "query": "薫る花は凛と咲く 1",
              "title": "薫る花は凛と咲く（１） (マガジンポケットコミックス)",
              "isbn13": null,
              "asin": "B09TF1DNJZ",
              "image": "https://m.media-amazon.com/images/I/51ZHjkFQUSL._SL500_.jpg",
              "score": 570
            }
          },
          {
            "query": "薫る花は凛と咲く 1 コミックス",
            "ok": true,
            "returned": 3,
            "best": {
              "source": "paapi_search",
              "query": "薫る花は凛と咲く 1 コミックス",
              "title": "薫る花は凛と咲く（１） (マガジンポケットコミックス)",
              "isbn13": null,
              "asin": "B09TF1DNJZ",
              "image": "https://m.media-amazon.com/images/I/51ZHjkFQUSL._SL500_.jpg",
              "score": 570
            }
          },
          {
            "query": "薫る花は凛と咲く 1 (コミックス)",
            "ok": true,
            "returned": 3,
            "best": {
              "source": "paapi_search",
              "query": "薫る花は凛と咲く 1 (コミックス)",
              "title": "薫る花は凛と咲く（１） (マガジンポケットコミックス)",
              "isbn13": null,
              "asin": "B09TF1DNJZ",
              "image": "https://m.media-amazon.com/images/I/51ZHjkFQUSL._SL500_.jpg",
              "score": 570
            }
          }
        ],
        "best": {
          "source": "paapi_search",
          "query": "薫る花は凛と咲く (1)",
          "title": "薫る花は凛と咲く（１） (マガジンポケットコミックス)",
          "isbn13": null,
          "asin": "B09TF1DNJZ",
          "image": "https://m.media-amazon.com/images/I/51ZHjkFQUSL._SL500_.jpg",
          "score": 570
        }
      },
      "paapiGet": {
        "ok": true,
        "json": {
          "ItemsResult": {
            "Items": [
              {
                "ASIN": "B09TF1DNJZ",
                "DetailPageURL": "https://www.amazon.co.jp/dp/B09TF1DNJZ?tag=book-scout-22&linkCode=ogi&th=1&psc=1",
                "Images": {
                  "Primary": {
                    "Large": {
                      "Height": 500,
                      "URL": "https://m.media-amazon.com/images/I/51ZHjkFQUSL._SL500_.jpg",
                      "Width": 378
                    }
                  }
                },
                "ItemInfo": {
                  "ByLineInfo": {
                    "Brand": {
                      "DisplayValue": "講談社",
                      "Label": "Brand",
                      "Locale": "ja_JP"
                    },
                    "Contributors": [
                      {
                        "Locale": "ja_JP",
                        "Name": "三香見サカ",
                        "Role": "著",
                        "RoleType": "author"
                      }
                    ],
                    "Manufacturer": {
                      "DisplayValue": "講談社",
                      "Label": "Manufacturer",
                      "Locale": "ja_JP"
                    }
                  },
                  "Title": {
                    "DisplayValue": "薫る花は凛と咲く（１） (マガジンポケットコミックス)",
                    "Label": "Title",
                    "Locale": "ja_JP"
                  }
                }
              }
            ]
          }
        }
      }
    }
  ]
}