{
  "version": 1,
  "updatedAt": "2026-03-30T15:38:42.027Z",
  "updatedAtJst": "2026-03-31 00:38:42",
  "dataset": "book_scout_events",
  "days": 30,
  "id": "rate_by_series_key",
  "columns": [
    {
      "name": "seriesKey",
      "type": "String"
    },
    {
      "name": "k",
      "type": "String"
    },
    {
      "name": "avg",
      "type": "Float64"
    },
    {
      "name": "n",
      "type": "UInt64"
    }
  ],
  "rows": [
    {
      "seriesKey": "乙嫁語り",
      "k": "art",
      "avg": 5,
      "n": "1"
    },
    {
      "seriesKey": "リアル",
      "k": "art",
      "avg": 4.5,
      "n": "2"
    },
    {
      "seriesKey": "アイシールド21",
      "k": "art",
      "avg": 4.5,
      "n": "2"
    },
    {
      "seriesKey": "ONE PIECE",
      "k": "art",
      "avg": 4.222222222222222,
      "n": "9"
    },
    {
      "seriesKey": "蟲師",
      "k": "art",
      "avg": 4,
      "n": "2"
    },
    {
      "seriesKey": "ノラガミ",
      "k": "art",
      "avg": 4,
      "n": "1"
    },
    {
      "seriesKey": "ちはやふる",
      "k": "art",
      "avg": 4,
      "n": "1"
    },
    {
      "seriesKey": "アオハライド",
      "k": "art",
      "avg": 4,
      "n": "1"
    },
    {
      "seriesKey": "銀魂",
      "k": "art",
      "avg": 4,
      "n": "1"
    },
    {
      "seriesKey": "監獄学園",
      "k": "art",
      "avg": 4,
      "n": "1"
    },
    {
      "seriesKey": "【推しの子】",
      "k": "art",
      "avg": 4,
      "n": "1"
    },
    {
      "seriesKey": "ヴィンランド・サガ",
      "k": "art",
      "avg": 4,
      "n": "1"
    },
    {
      "seriesKey": "ドラゴンボール",
      "k": "art",
      "avg": 4,
      "n": "1"
    },
    {
      "seriesKey": "NARUTO -ナルト-",
      "k": "art",
      "avg": 3.8,
      "n": "5"
    },
    {
      "seriesKey": "君は淫らな僕の女王",
      "k": "art",
      "avg": 3.5,
      "n": "2"
    },
    {
      "seriesKey": "ベルセルク",
      "k": "art",
      "avg": 3.5,
      "n": "2"
    },
    {
      "seriesKey": "アクタージュ act-age",
      "k": "art",
      "avg": 3.5,
      "n": "2"
    },
    {
      "seriesKey": "フルーツバスケット",
      "k": "art",
      "avg": 3,
      "n": "3"
    },
    {
      "seriesKey": "ニセコイ",
      "k": "art",
      "avg": 3,
      "n": "3"
    },
    {
      "seriesKey": "少年のアビス",
      "k": "art",
      "avg": 3,
      "n": "2"
    },
    {
      "seriesKey": "君に届け",
      "k": "art",
      "avg": 3,
      "n": "2"
    },
    {
      "seriesKey": "カッコウの許嫁",
      "k": "art",
      "avg": 3,
      "n": "2"
    },
    {
      "seriesKey": "神のみぞ知るセカイ",
      "k": "art",
      "avg": 3,
      "n": "2"
    },
    {
      "seriesKey": "からかい上手の高木さん",
      "k": "art",
      "avg": 3,
      "n": "2"
    },
    {
      "seriesKey": "彼女、お借りします",
      "k": "art",
      "avg": 3,
      "n": "2"
    },
    {
      "seriesKey": "トモちゃんは女の子!",
      "k": "art",
      "avg": 3,
      "n": "2"
    },
    {
      "seriesKey": "終わりのセラフ",
      "k": "art",
      "avg": 3,
      "n": "1"
    },
    {
      "seriesKey": "ドラゴンボール超",
      "k": "art",
      "avg": 3,
      "n": "1"
    },
    {
      "seriesKey": "蜘蛛ですが、なにか？",
      "k": "art",
      "avg": 3,
      "n": "1"
    },
    {
      "seriesKey": "タコピーの原罪",
      "k": "art",
      "avg": 3,
      "n": "1"
    },
    {
      "seriesKey": "ひるなかの流星",
      "k": "art",
      "avg": 3,
      "n": "1"
    },
    {
      "seriesKey": "ホリミヤ",
      "k": "art",
      "avg": 3,
      "n": "1"
    },
    {
      "seriesKey": "政宗くんのリベンジ",
      "k": "art",
      "avg": 3,
      "n": "1"
    },
    {
      "seriesKey": "ひげを剃る。そして女子高生を拾う。",
      "k": "art",
      "avg": 3,
      "n": "1"
    },
    {
      "seriesKey": "ヨコハマ買い出し紀行",
      "k": "art",
      "avg": 3,
      "n": "1"
    },
    {
      "seriesKey": "ゆびさきと恋々",
      "k": "art",
      "avg": 3,
      "n": "1"
    },
    {
      "seriesKey": "同級生",
      "k": "art",
      "avg": 3,
      "n": "1"
    },
    {
      "seriesKey": "3月のライオン",
      "k": "art",
      "avg": 3,
      "n": "1"
    },
    {
      "seriesKey": "双星の陰陽師",
      "k": "art",
      "avg": 3,
      "n": "1"
    },
    {
      "seriesKey": "アオのハコ",
      "k": "art",
      "avg": 3,
      "n": "1"
    },
    {
      "seriesKey": "ぼくたちは勉強ができない",
      "k": "art",
      "avg": 3,
      "n": "1"
    },
    {
      "seriesKey": "orange [オレンジ]",
      "k": "art",
      "avg": 3,
      "n": "1"
    },
    {
      "seriesKey": "五等分の花嫁",
      "k": "art",
      "avg": 3,
      "n": "1"
    },
    {
      "seriesKey": "ソウルイーター",
      "k": "art",
      "avg": 3,
      "n": "1"
    },
    {
      "seriesKey": "魔男のイチ",
      "k": "art",
      "avg": 3,
      "n": "1"
    },
    {
      "seriesKey": "HUNTER×HUNTER",
      "k": "art",
      "avg": 3,
      "n": "1"
    },
    {
      "seriesKey": "この音とまれ！",
      "k": "art",
      "avg": 3,
      "n": "1"
    },
    {
      "seriesKey": "ジョジョの奇妙な冒険 ストーンオーシャン",
      "k": "art",
      "avg": 3,
      "n": "1"
    },
    {
      "seriesKey": "あせとせっけん",
      "k": "art",
      "avg": 3,
      "n": "1"
    },
    {
      "seriesKey": "ガンバレ！中村くん！！",
      "k": "art",
      "avg": 3,
      "n": "1"
    },
    {
      "seriesKey": "亜人",
      "k": "art",
      "avg": 3,
      "n": "1"
    },
    {
      "seriesKey": "イジらないで、長瀞さん",
      "k": "art",
      "avg": 3,
      "n": "1"
    },
    {
      "seriesKey": "約束のネバーランド",
      "k": "art",
      "avg": 3,
      "n": "1"
    },
    {
      "seriesKey": "宝石の国",
      "k": "art",
      "avg": 3,
      "n": "1"
    },
    {
      "seriesKey": "青の祓魔師",
      "k": "art",
      "avg": 3,
      "n": "1"
    },
    {
      "seriesKey": "日々蝶々",
      "k": "art",
      "avg": 3,
      "n": "1"
    },
    {
      "seriesKey": "血の轍",
      "k": "art",
      "avg": 3,
      "n": "1"
    },
    {
      "seriesKey": "ボーイミーツマリア",
      "k": "art",
      "avg": 3,
      "n": "1"
    },
    {
      "seriesKey": "ドロヘドロ",
      "k": "art",
      "avg": 3,
      "n": "1"
    },
    {
      "seriesKey": "ケンガンアシュラ",
      "k": "art",
      "avg": 3,
      "n": "1"
    },
    {
      "seriesKey": "ラストゲーム",
      "k": "art",
      "avg": 3,
      "n": "1"
    },
    {
      "seriesKey": "寄生獣",
      "k": "art",
      "avg": 3,
      "n": "1"
    },
    {
      "seriesKey": "マギ",
      "k": "art",
      "avg": 3,
      "n": "1"
    },
    {
      "seriesKey": "ソラニン",
      "k": "art",
      "avg": 3,
      "n": "1"
    },
    {
      "seriesKey": "とつくにの少女",
      "k": "art",
      "avg": 3,
      "n": "1"
    },
    {
      "seriesKey": "東京卍リベンジャーズ",
      "k": "art",
      "avg": 3,
      "n": "1"
    },
    {
      "seriesKey": "神様はじめました",
      "k": "art",
      "avg": 3,
      "n": "1"
    },
    {
      "seriesKey": "惑星のさみだれ",
      "k": "art",
      "avg": 3,
      "n": "1"
    },
    {
      "seriesKey": "月刊少女野崎くん",
      "k": "art",
      "avg": 3,
      "n": "1"
    },
    {
      "seriesKey": "ドメスティックな彼女",
      "k": "art",
      "avg": 3,
      "n": "1"
    },
    {
      "seriesKey": "幽☆遊☆白書",
      "k": "art",
      "avg": 2,
      "n": "2"
    },
    {
      "seriesKey": "徒然チルドレン",
      "k": "art",
      "avg": 2,
      "n": "1"
    },
    {
      "seriesKey": "キングダム",
      "k": "art",
      "avg": 2,
      "n": "1"
    },
    {
      "seriesKey": "ReLIFE",
      "k": "art",
      "avg": 2,
      "n": "1"
    },
    {
      "seriesKey": "君のことが大大大大大好きな100人の彼女",
      "k": "art",
      "avg": 2,
      "n": "1"
    },
    {
      "seriesKey": "ゴールデンカムイ",
      "k": "art",
      "avg": 2,
      "n": "1"
    },
    {
      "seriesKey": "金色のガッシュ!!",
      "k": "art",
      "avg": 2,
      "n": "1"
    },
    {
      "seriesKey": "道産子ギャルはなまらめんこい",
      "k": "art",
      "avg": 1,
      "n": "1"
    },
    {
      "seriesKey": "蟲師",
      "k": "rec",
      "avg": 5,
      "n": "2"
    },
    {
      "seriesKey": "金色のガッシュ!!",
      "k": "rec",
      "avg": 5,
      "n": "1"
    },
    {
      "seriesKey": "魔男のイチ",
      "k": "rec",
      "avg": 5,
      "n": "1"
    },
    {
      "seriesKey": "HUNTER×HUNTER",
      "k": "rec",
      "avg": 5,
      "n": "1"
    },
    {
      "seriesKey": "寄生獣",
      "k": "rec",
      "avg": 5,
      "n": "1"
    },
    {
      "seriesKey": "ONE PIECE",
      "k": "rec",
      "avg": 4.888888888888889,
      "n": "9"
    },
    {
      "seriesKey": "幽☆遊☆白書",
      "k": "rec",
      "avg": 4.5,
      "n": "2"
    },
    {
      "seriesKey": "フルーツバスケット",
      "k": "rec",
      "avg": 4.333333333333333,
      "n": "3"
    },
    {
      "seriesKey": "君は淫らな僕の女王",
      "k": "rec",
      "avg": 4,
      "n": "2"
    },
    {
      "seriesKey": "君に届け",
      "k": "rec",
      "avg": 4,
      "n": "2"
    },
    {
      "seriesKey": "ベルセルク",
      "k": "rec",
      "avg": 4,
      "n": "2"
    },
    {
      "seriesKey": "アイシールド21",
      "k": "rec",
      "avg": 4,
      "n": "2"
    },
    {
      "seriesKey": "リアル",
      "k": "rec",
      "avg": 4,
      "n": "2"
    },
    {
      "seriesKey": "ノラガミ",
      "k": "rec",
      "avg": 4,
      "n": "1"
    },
    {
      "seriesKey": "ひげを剃る。そして女子高生を拾う。",
      "k": "rec",
      "avg": 4,
      "n": "1"
    },
    {
      "seriesKey": "青の祓魔師",
      "k": "rec",
      "avg": 4,
      "n": "1"
    },
    {
      "seriesKey": "キングダム",
      "k": "rec",
      "avg": 4,
      "n": "1"
    },
    {
      "seriesKey": "ゴールデンカムイ",
      "k": "rec",
      "avg": 4,
      "n": "1"
    },
    {
      "seriesKey": "ドラゴンボール",
      "k": "rec",
      "avg": 4,
      "n": "1"
    },
    {
      "seriesKey": "宝石の国",
      "k": "rec",
      "avg": 4,
      "n": "1"
    },
    {
      "seriesKey": "orange [オレンジ]",
      "k": "rec",
      "avg": 4,
      "n": "1"
    },
    {
      "seriesKey": "血の轍",
      "k": "rec",
      "avg": 4,
      "n": "1"
    },
    {
      "seriesKey": "3月のライオン",
      "k": "rec",
      "avg": 4,
      "n": "1"
    },
    {
      "seriesKey": "亜人",
      "k": "rec",
      "avg": 4,
      "n": "1"
    },
    {
      "seriesKey": "タコピーの原罪",
      "k": "rec",
      "avg": 4,
      "n": "1"
    },
    {
      "seriesKey": "監獄学園",
      "k": "rec",
      "avg": 4,
      "n": "1"
    },
    {
      "seriesKey": "ReLIFE",
      "k": "rec",
      "avg": 4,
      "n": "1"
    },
    {
      "seriesKey": "ちはやふる",
      "k": "rec",
      "avg": 4,
      "n": "1"
    },
    {
      "seriesKey": "【推しの子】",
      "k": "rec",
      "avg": 4,
      "n": "1"
    },
    {
      "seriesKey": "ヴィンランド・サガ",
      "k": "rec",
      "avg": 4,
      "n": "1"
    },
    {
      "seriesKey": "NARUTO -ナルト-",
      "k": "rec",
      "avg": 3.8,
      "n": "5"
    },
    {
      "seriesKey": "からかい上手の高木さん",
      "k": "rec",
      "avg": 3.5,
      "n": "2"
    },
    {
      "seriesKey": "カッコウの許嫁",
      "k": "rec",
      "avg": 3.5,
      "n": "2"
    },
    {
      "seriesKey": "少年のアビス",
      "k": "rec",
      "avg": 3.5,
      "n": "2"
    },
    {
      "seriesKey": "ニセコイ",
      "k": "rec",
      "avg": 3,
      "n": "3"
    },
    {
      "seriesKey": "神のみぞ知るセカイ",
      "k": "rec",
      "avg": 3,
      "n": "2"
    },
    {
      "seriesKey": "アクタージュ act-age",
      "k": "rec",
      "avg": 3,
      "n": "2"
    },
    {
      "seriesKey": "トモちゃんは女の子!",
      "k": "rec",
      "avg": 3,
      "n": "2"
    },
    {
      "seriesKey": "彼女、お借りします",
      "k": "rec",
      "avg": 3,
      "n": "2"
    },
    {
      "seriesKey": "アオハライド",
      "k": "rec",
      "avg": 3,
      "n": "1"
    },
    {
      "seriesKey": "イジらないで、長瀞さん",
      "k": "rec",
      "avg": 3,
      "n": "1"
    },
    {
      "seriesKey": "ぼくたちは勉強ができない",
      "k": "rec",
      "avg": 3,
      "n": "1"
    },
    {
      "seriesKey": "蜘蛛ですが、なにか？",
      "k": "rec",
      "avg": 3,
      "n": "1"
    },
    {
      "seriesKey": "ソウルイーター",
      "k": "rec",
      "avg": 3,
      "n": "1"
    },
    {
      "seriesKey": "神様はじめました",
      "k": "rec",
      "avg": 3,
      "n": "1"
    },
    {
      "seriesKey": "政宗くんのリベンジ",
      "k": "rec",
      "avg": 3,
      "n": "1"
    },
    {
      "seriesKey": "乙嫁語り",
      "k": "rec",
      "avg": 3,
      "n": "1"
    },
    {
      "seriesKey": "あせとせっけん",
      "k": "rec",
      "avg": 3,
      "n": "1"
    },
    {
      "seriesKey": "ホリミヤ",
      "k": "rec",
      "avg": 3,
      "n": "1"
    },
    {
      "seriesKey": "同級生",
      "k": "rec",
      "avg": 3,
      "n": "1"
    },
    {
      "seriesKey": "アオのハコ",
      "k": "rec",
      "avg": 3,
      "n": "1"
    },
    {
      "seriesKey": "ソラニン",
      "k": "rec",
      "avg": 3,
      "n": "1"
    },
    {
      "seriesKey": "この音とまれ！",
      "k": "rec",
      "avg": 3,
      "n": "1"
    },
    {
      "seriesKey": "日々蝶々",
      "k": "rec",
      "avg": 3,
      "n": "1"
    },
    {
      "seriesKey": "ラストゲーム",
      "k": "rec",
      "avg": 3,
      "n": "1"
    },
    {
      "seriesKey": "マギ",
      "k": "rec",
      "avg": 3,
      "n": "1"
    },
    {
      "seriesKey": "とつくにの少女",
      "k": "rec",
      "avg": 3,
      "n": "1"
    },
    {
      "seriesKey": "君のことが大大大大大好きな100人の彼女",
      "k": "rec",
      "avg": 3,
      "n": "1"
    },
    {
      "seriesKey": "ジョジョの奇妙な冒険 ストーンオーシャン",
      "k": "rec",
      "avg": 3,
      "n": "1"
    },
    {
      "seriesKey": "徒然チルドレン",
      "k": "rec",
      "avg": 3,
      "n": "1"
    },
    {
      "seriesKey": "五等分の花嫁",
      "k": "rec",
      "avg": 3,
      "n": "1"
    },
    {
      "seriesKey": "惑星のさみだれ",
      "k": "rec",
      "avg": 3,
      "n": "1"
    },
    {
      "seriesKey": "ドラゴンボール超",
      "k": "rec",
      "avg": 3,
      "n": "1"
    },
    {
      "seriesKey": "終わりのセラフ",
      "k": "rec",
      "avg": 3,
      "n": "1"
    },
    {
      "seriesKey": "ヨコハマ買い出し紀行",
      "k": "rec",
      "avg": 3,
      "n": "1"
    },
    {
      "seriesKey": "ガンバレ！中村くん！！",
      "k": "rec",
      "avg": 3,
      "n": "1"
    },
    {
      "seriesKey": "ボーイミーツマリア",
      "k": "rec",
      "avg": 3,
      "n": "1"
    },
    {
      "seriesKey": "双星の陰陽師",
      "k": "rec",
      "avg": 3,
      "n": "1"
    },
    {
      "seriesKey": "東京卍リベンジャーズ",
      "k": "rec",
      "avg": 3,
      "n": "1"
    },
    {
      "seriesKey": "約束のネバーランド",
      "k": "rec",
      "avg": 3,
      "n": "1"
    },
    {
      "seriesKey": "月刊少女野崎くん",
      "k": "rec",
      "avg": 3,
      "n": "1"
    },
    {
      "seriesKey": "ひるなかの流星",
      "k": "rec",
      "avg": 3,
      "n": "1"
    },
    {
      "seriesKey": "ドメスティックな彼女",
      "k": "rec",
      "avg": 3,
      "n": "1"
    },
    {
      "seriesKey": "ゆびさきと恋々",
      "k": "rec",
      "avg": 3,
      "n": "1"
    },
    {
      "seriesKey": "銀魂",
      "k": "rec",
      "avg": 3,
      "n": "1"
    },
    {
      "seriesKey": "ケンガンアシュラ",
      "k": "rec",
      "avg": 3,
      "n": "1"
    },
    {
      "seriesKey": "ドロヘドロ",
      "k": "rec",
      "avg": 3,
      "n": "1"
    },
    {
      "seriesKey": "道産子ギャルはなまらめんこい",
      "k": "rec",
      "avg": 2,
      "n": "1"
    }
  ],
  "raw": {
    "rows": 156,
    "rows_before_limit_at_least": 216
  }
}