{
  "version": 1,
  "updatedAt": "2026-03-23T07:38:40.842Z",
  "updatedAtJst": "2026-03-23 16:38:40",
  "dataset": "book_scout_events",
  "days": 30,
  "id": "type_counts",
  "columns": [
    {
      "name": "type",
      "type": "String"
    },
    {
      "name": "n",
      "type": "UInt64"
    }
  ],
  "rows": [
    {
      "type": "favorite",
      "n": "827"
    },
    {
      "type": "work_view",
      "n": "588"
    },
    {
      "type": "rate",
      "n": "393"
    },
    {
      "type": "vote",
      "n": "319"
    },
    {
      "type": "list_filter",
      "n": "221"
    },
    {
      "type": "mood_fb",
      "n": "55"
    }
  ],
  "raw": {
    "rows": 6,
    "rows_before_limit_at_least": 2403
  }
}