{
  "version": 1,
  "updatedAt": "2026-04-03T10:02:10.298Z",
  "updatedAtJst": "2026-04-03 19:02:10",
  "dataset": "book_scout_events",
  "days": 30,
  "id": "type_counts",
  "columns": [
    {
      "name": "type",
      "type": "String"
    },
    {
      "name": "n",
      "type": "UInt64"
    }
  ],
  "rows": [
    {
      "type": "favorite",
      "n": "480"
    },
    {
      "type": "work_view",
      "n": "169"
    },
    {
      "type": "vote",
      "n": "56"
    },
    {
      "type": "rate",
      "n": "56"
    },
    {
      "type": "mood_fb",
      "n": "33"
    },
    {
      "type": "list_filter",
      "n": "31"
    }
  ],
  "raw": {
    "rows": 6,
    "rows_before_limit_at_least": 825
  }
}