{
  "version": 1,
  "updatedAt": "2026-02-21T11:33:46.098Z",
  "dataset": "book_scout_events",
  "days": 30,
  "id": "type_counts",
  "columns": [
    {
      "name": "type",
      "type": "String"
    },
    {
      "name": "n",
      "type": "UInt64"
    }
  ],
  "rows": [
    {
      "type": "list_filter",
      "n": "162"
    },
    {
      "type": "vote",
      "n": "47"
    },
    {
      "type": "work_view",
      "n": "12"
    },
    {
      "type": "favorite",
      "n": "8"
    },
    {
      "type": "__verify",
      "n": "7"
    },
    {
      "type": "test",
      "n": "6"
    },
    {
      "type": "unknown",
      "n": "1"
    }
  ],
  "raw": {
    "rows": 7,
    "rows_before_limit_at_least": 235
  }
}