{
  "version": 1,
  "updatedAt": "2026-03-30T07:59:42.740Z",
  "updatedAtJst": "2026-03-30 16:59:42",
  "dataset": "book_scout_events",
  "days": 30,
  "id": "type_counts",
  "columns": [
    {
      "name": "type",
      "type": "String"
    },
    {
      "name": "n",
      "type": "UInt64"
    }
  ],
  "rows": [
    {
      "type": "favorite",
      "n": "751"
    },
    {
      "type": "work_view",
      "n": "360"
    },
    {
      "type": "rate",
      "n": "220"
    },
    {
      "type": "vote",
      "n": "200"
    },
    {
      "type": "list_filter",
      "n": "172"
    },
    {
      "type": "mood_fb",
      "n": "55"
    }
  ],
  "raw": {
    "rows": 6,
    "rows_before_limit_at_least": 1758
  }
}